<?xml version="1.0" encoding="UTF-8"?>

<FindBugsFilter xmlns="https://github.com/spotbugs/filter/3.0.0" xmlns:xsi="http://www.w3.org/2001/XMLSchema-instance"
                xsi:schemaLocation="https://github.com/spotbugs/filter/3.0.0 https://raw.githubusercontent.com/spotbugs/spotbugs/3.1.0/spotbugs/etc/findbugsfilter.xsd">
  <Match>
    <Bug pattern="EI_EXPOSE_REP" />
    <Or>
      <Class name="com.azure.messaging.eventgrid.EventGridEvent" />
      <Class name="com.azure.messaging.eventgrid.implementation.models.AcsRouterCommunicationError" />
      <Class name="com.azure.messaging.eventgrid.implementation.models.CloudEvent" />
      <Class name="com.azure.messaging.eventgrid.systemevents.AcsChatMessageEditedEventData" />
      <Class name="com.azure.messaging.eventgrid.systemevents.AcsChatMessageEditedInThreadEventData" />
      <Class name="com.azure.messaging.eventgrid.systemevents.AcsChatMessageReceivedEventData" />
      <Class name="com.azure.messaging.eventgrid.systemevents.AcsChatMessageReceivedInThreadEventData" />
      <Class name="com.azure.messaging.eventgrid.systemevents.AcsChatThreadCreatedEventData" />
      <Class name="com.azure.messaging.eventgrid.systemevents.AcsChatThreadCreatedWithUserEventData" />
      <Class name="com.azure.messaging.eventgrid.systemevents.AcsChatThreadParticipantProperties" />
      <Class name="com.azure.messaging.eventgrid.systemevents.AcsChatThreadPropertiesUpdatedEventData" />
      <Class name="com.azure.messaging.eventgrid.systemevents.AcsChatThreadPropertiesUpdatedPerUserEventData" />
      <Class name="com.azure.messaging.eventgrid.systemevents.AcsIncomingCallCustomContext" />
      <Class name="com.azure.messaging.eventgrid.systemevents.AcsRecordingStorageInfoProperties" />
      <Class name="com.azure.messaging.eventgrid.systemevents.AcsRouterJobClassifiedEventData" />
      <Class name="com.azure.messaging.eventgrid.systemevents.AcsRouterJobEventData" />
      <Class name="com.azure.messaging.eventgrid.systemevents.AcsRouterJobQueuedEventData" />
      <Class name="com.azure.messaging.eventgrid.systemevents.AcsRouterJobReceivedEventData" />
      <Class name="com.azure.messaging.eventgrid.systemevents.AcsRouterJobSchedulingFailedEventData" />
      <Class name="com.azure.messaging.eventgrid.systemevents.AcsRouterJobWaitingForActivationEventData" />
      <Class name="com.azure.messaging.eventgrid.systemevents.AcsRouterJobWorkerSelectorsExpiredEventData" />
      <Class name="com.azure.messaging.eventgrid.systemevents.AcsRouterQueueDetails" />
      <Class name="com.azure.messaging.eventgrid.systemevents.AcsRouterWorkerOfferAcceptedEventData" />
      <Class name="com.azure.messaging.eventgrid.systemevents.AcsRouterWorkerOfferIssuedEventData" />
      <Class name="com.azure.messaging.eventgrid.systemevents.AcsRouterWorkerRegisteredEventData" />
      <Class name="com.azure.messaging.eventgrid.systemevents.AcsRouterWorkerUpdatedEventData" />
      <Class name="com.azure.messaging.eventgrid.systemevents.AcsSmsDeliveryReportReceivedEventData" />
      <Class name="com.azure.messaging.eventgrid.systemevents.AvsClusterEventData" />
      <Class name="com.azure.messaging.eventgrid.systemevents.AvsScriptExecutionEventData" />
      <Class name="com.azure.messaging.eventgrid.systemevents.AvsScriptExecutionFinishedEventData" />
      <Class name="com.azure.messaging.eventgrid.systemevents.DeviceTelemetryEventProperties" />
      <Class name="com.azure.messaging.eventgrid.systemevents.EventGridMqttClientCreatedOrUpdatedEventData" />
      <Class name="com.azure.messaging.eventgrid.systemevents.MapsGeofenceEventProperties" />
      <Class name="com.azure.messaging.eventgrid.systemevents.MediaJobCanceledEventData" />
      <Class name="com.azure.messaging.eventgrid.systemevents.MediaJobError" />
      <Class name="com.azure.messaging.eventgrid.systemevents.MediaJobErroredEventData" />
      <Class name="com.azure.messaging.eventgrid.systemevents.MediaJobFinishedEventData" />
      <Class name="com.azure.messaging.eventgrid.systemevents.MediaJobOutputProgressEventData" />
      <Class name="com.azure.messaging.eventgrid.systemevents.MediaJobOutputStateChangeEventData" />
      <Class name="com.azure.messaging.eventgrid.systemevents.MediaJobStateChangeEventData" />
      <Class name="com.azure.messaging.eventgrid.systemevents.ResourceActionCancelEventData" />
      <Class name="com.azure.messaging.eventgrid.systemevents.ResourceActionFailureEventData" />
      <Class name="com.azure.messaging.eventgrid.systemevents.ResourceActionSuccessEventData" />
      <Class name="com.azure.messaging.eventgrid.systemevents.ResourceAuthorization" />
      <Class name="com.azure.messaging.eventgrid.systemevents.ResourceDeleteCancelEventData" />
      <Class name="com.azure.messaging.eventgrid.systemevents.ResourceDeleteFailureEventData" />
      <Class name="com.azure.messaging.eventgrid.systemevents.ResourceDeleteSuccessEventData" />
      <Class name="com.azure.messaging.eventgrid.systemevents.ResourceNotificationsResourceUpdatedDetails" />
      <Class name="com.azure.messaging.eventgrid.systemevents.ResourceWriteCancelEventData" />
      <Class name="com.azure.messaging.eventgrid.systemevents.ResourceWriteFailureEventData" />
      <Class name="com.azure.messaging.eventgrid.systemevents.ResourceWriteSuccessEventData" />
    </Or>
  </Match>
  <Match>
    <Bug pattern="EI_EXPOSE_REP2" />
    <Or>
      <Class name="com.azure.messaging.eventgrid.EventGridEvent" />
      <Class name="com.azure.messaging.eventgrid.EventGridPublisherClientBuilder" />
      <Class name="com.azure.messaging.eventgrid.implementation.CloudEventTracingPipelinePolicy" />
      <Class name="com.azure.messaging.eventgrid.implementation.EventGridPublisherClientImplBuilder" />
      <Class name="com.azure.messaging.eventgrid.implementation.models.AcsRouterCommunicationError" />
      <Class name="com.azure.messaging.eventgrid.implementation.models.CloudEvent" />
      <Class name="com.azure.messaging.eventgrid.systemevents.AcsChatMessageEditedEventData" />
      <Class name="com.azure.messaging.eventgrid.systemevents.AcsChatMessageEditedInThreadEventData" />
      <Class name="com.azure.messaging.eventgrid.systemevents.AcsChatMessageReceivedEventData" />
      <Class name="com.azure.messaging.eventgrid.systemevents.AcsChatMessageReceivedInThreadEventData" />
      <Class name="com.azure.messaging.eventgrid.systemevents.AcsChatThreadCreatedEventData" />
      <Class name="com.azure.messaging.eventgrid.systemevents.AcsChatThreadCreatedWithUserEventData" />
      <Class name="com.azure.messaging.eventgrid.systemevents.AcsChatThreadParticipantProperties" />
      <Class name="com.azure.messaging.eventgrid.systemevents.AcsChatThreadPropertiesUpdatedEventData" />
      <Class name="com.azure.messaging.eventgrid.systemevents.AcsChatThreadPropertiesUpdatedPerUserEventData" />
      <Class name="com.azure.messaging.eventgrid.systemevents.AcsIncomingCallCustomContext" />
      <Class name="com.azure.messaging.eventgrid.systemevents.AcsRecordingStorageInfoProperties" />
      <Class name="com.azure.messaging.eventgrid.systemevents.AcsRouterJobClassifiedEventData" />
      <Class name="com.azure.messaging.eventgrid.systemevents.AcsRouterJobEventData" />
      <Class name="com.azure.messaging.eventgrid.systemevents.AcsRouterJobQueuedEventData" />
      <Class name="com.azure.messaging.eventgrid.systemevents.AcsRouterJobReceivedEventData" />
      <Class name="com.azure.messaging.eventgrid.systemevents.AcsRouterJobSchedulingFailedEventData" />
      <Class name="com.azure.messaging.eventgrid.systemevents.AcsRouterJobWaitingForActivationEventData" />
      <Class name="com.azure.messaging.eventgrid.systemevents.AcsRouterJobWorkerSelectorsExpiredEventData" />
      <Class name="com.azure.messaging.eventgrid.systemevents.AcsRouterQueueDetails" />
      <Class name="com.azure.messaging.eventgrid.systemevents.AcsRouterWorkerOfferAcceptedEventData" />
      <Class name="com.azure.messaging.eventgrid.systemevents.AcsRouterWorkerOfferIssuedEventData" />
      <Class name="com.azure.messaging.eventgrid.systemevents.AcsRouterWorkerRegisteredEventData" />
      <Class name="com.azure.messaging.eventgrid.systemevents.AcsRouterWorkerUpdatedEventData" />
      <Class name="com.azure.messaging.eventgrid.systemevents.AcsSmsDeliveryReportReceivedEventData" />
      <Class name="com.azure.messaging.eventgrid.systemevents.AvsClusterEventData" />
      <Class name="com.azure.messaging.eventgrid.systemevents.AvsScriptExecutionEventData" />
      <Class name="com.azure.messaging.eventgrid.systemevents.AvsScriptExecutionFinishedEventData" />
      <Class name="com.azure.messaging.eventgrid.systemevents.DeviceTelemetryEventProperties" />
      <Class name="com.azure.messaging.eventgrid.systemevents.EventGridMqttClientCreatedOrUpdatedEventData" />
      <Class name="com.azure.messaging.eventgrid.systemevents.MapsGeofenceEventProperties" />
      <Class name="com.azure.messaging.eventgrid.systemevents.MediaJobCanceledEventData" />
      <Class name="com.azure.messaging.eventgrid.systemevents.MediaJobErroredEventData" />
      <Class name="com.azure.messaging.eventgrid.systemevents.MediaJobFinishedEventData" />
      <Class name="com.azure.messaging.eventgrid.systemevents.MediaJobOutputProgressEventData" />
      <Class name="com.azure.messaging.eventgrid.systemevents.MediaJobOutputStateChangeEventData" />
      <Class name="com.azure.messaging.eventgrid.systemevents.MediaJobStateChangeEventData" />
      <Class name="com.azure.messaging.eventgrid.systemevents.ResourceActionCancelEventData" />
      <Class name="com.azure.messaging.eventgrid.systemevents.ResourceActionFailureEventData" />
      <Class name="com.azure.messaging.eventgrid.systemevents.ResourceActionSuccessEventData" />
      <Class name="com.azure.messaging.eventgrid.systemevents.ResourceAuthorization" />
      <Class name="com.azure.messaging.eventgrid.systemevents.ResourceDeleteCancelEventData" />
      <Class name="com.azure.messaging.eventgrid.systemevents.ResourceDeleteFailureEventData" />
      <Class name="com.azure.messaging.eventgrid.systemevents.ResourceDeleteSuccessEventData" />
      <Class name="com.azure.messaging.eventgrid.systemevents.ResourceNotificationsResourceUpdatedDetails" />
      <Class name="com.azure.messaging.eventgrid.systemevents.ResourceWriteCancelEventData" />
      <Class name="com.azure.messaging.eventgrid.systemevents.ResourceWriteFailureEventData" />
      <Class name="com.azure.messaging.eventgrid.systemevents.ResourceWriteSuccessEventData" />
    </Or>
  </Match>
  <Match>
    <Bug pattern="NM_CONFUSING" />
    <Or>
      <Class name="com.azure.messaging.eventgrid.systemevents.AcsEmailEngagementTrackingReportReceivedEventData" />
      <Class name="com.azure.messaging.eventgrid.systemevents.AppConfigurationKeyValueDeletedEventData" />
    </Or>
  </Match>
  <Match>
    <Bug pattern="UPM_UNCALLED_PRIVATE_METHOD" />
    <Class name="com.azure.messaging.eventgrid.implementation.models.EventGridEvent" />
  </Match>
  <Match>
    <Bug pattern="UWF_FIELD_NOT_INITIALIZED_IN_CONSTRUCTOR" />
    <Or>
      <Class name="com.azure.messaging.eventgrid.EventGridPublisherClientBuilder" />
      <Class name="com.azure.messaging.eventgrid.systemevents.AcsMessageEventData" />
      <Class name="com.azure.messaging.eventgrid.systemevents.AcsRouterJobClassificationFailedEventData" />
    </Or>
  </Match>
</FindBugsFilter>
